LICENCE.txt
README.txt
setup.py
wnk_tree_ai/__init__.py
wnk_tree_ai/wnk_tree_ai_creation.py
wnk_tree_ai/wnk_tree_ai_utils.py
wnk_tree_ai.egg-info/PKG-INFO
wnk_tree_ai.egg-info/SOURCES.txt
wnk_tree_ai.egg-info/dependency_links.txt
wnk_tree_ai.egg-info/requires.txt
wnk_tree_ai.egg-info/top_level.txt