Metadata-Version: 2.1
Name: wnk-tree-ai
Version: 0.0.13
Summary: Nomenclature for AI Traversal
Home-page: UNKNOWN
Author: Philipp Friebertshäuser
Author-email: friebertshaeuser@traide.ai
License: MIT
Keywords: wnk
Platform: UNKNOWN
License-File: LICENCE.txt
